.gitignore
LICENSE
README.md
setup.py
django_voximplant.egg-info/PKG-INFO
django_voximplant.egg-info/SOURCES.txt
django_voximplant.egg-info/dependency_links.txt
django_voximplant.egg-info/top_level.txt
voximplant/__init__.py
voximplant/admin.py
voximplant/api_client.py
voximplant/models.py
voximplant/tools.py
voximplant/urls.py
voximplant/management/__init__.py
voximplant/management/commands/__init__.py
voximplant/management/commands/vox_call_list_download.py
voximplant/management/commands/vox_call_list_recover.py
voximplant/management/commands/vox_call_list_start.py
voximplant/management/commands/vox_call_list_stop.py
voximplant/management/commands/vox_call_lists_check.py
voximplant/management/commands/vox_download.py
voximplant/management/commands/vox_upload.py
voximplant/migrations/0001_initial.py
voximplant/migrations/0002_auto_20160513_1716.py
voximplant/migrations/0003_auto_20160513_1838.py
voximplant/migrations/0004_auto_20160513_1846.py
voximplant/migrations/0005_rule_scenarios.py
voximplant/migrations/0006_calllist_calllistphone.py
voximplant/migrations/0007_auto_20160514_0557.py
voximplant/migrations/0008_auto_20160514_0800.py
voximplant/migrations/0009_auto_20160516_0649.py
voximplant/migrations/0010_auto_20160516_1257.py
voximplant/migrations/0011_auto_20160516_1738.py
voximplant/migrations/0012_auto_20160721_0716.py
voximplant/migrations/0013_auto_20170419_0930.py
voximplant/migrations/__init__.py