Metadata-Version: 1.1
Name: django-voximplant
Version: 0.0.8
Summary: Django application for VoxImplant integration.
Home-page: https://github.com/telminov/django-voximplant
Author: Telminov Sergey
Author-email: sergey@telminov.ru
License: The MIT License
Platform: UNKNOWN
Requires: django
Requires: requests
Requires: pyzmq
